ansy/__init__.py
ansy/__main__.py
ansy/_corpus_colors.py
ansy/_others.py
ansy/ansy.py
ansy/cli.py
ansy/colors.py
ansy/exceptions.py
ansy-1.1.3.dist-info/licenses/LICENSE
tests/__init__.py
tests/test_ansy.py
ansy-1.1.3.dist-info/METADATA
ansy-1.1.3.dist-info/WHEEL
ansy-1.1.3.dist-info/entry_points.txt
ansy-1.1.3.dist-info/top_level.txt
ansy-1.1.3.dist-info/RECORD
