Metadata-Version: 2.4
Name: ansy
Version: 1.1.3
Summary: A Python package to colorize and format output in the terminal.
Author-email: Anas Shakeel <srdranas456@gmail.com>
License-Expression: MIT
Project-URL: Documentation, https://anas-shakeel.github.io/ansy/
Project-URL: Homepage, https://github.com/anas-shakeel/ansy
Project-URL: Source, https://github.com/anas-shakeel/ansy
Keywords: python,ANSI,ANSI color,color,cli,command-line,terminal,text formatting,color output,ansy,terminal,text styling
Classifier: Development Status :: 5 - Production/Stable
Classifier: Environment :: Console
Classifier: Intended Audience :: Developers
Classifier: Operating System :: Microsoft :: Windows
Classifier: Operating System :: POSIX :: Linux
Classifier: Operating System :: MacOS
Classifier: Programming Language :: Python :: 3
Classifier: Programming Language :: Python :: 3 :: Only
Classifier: Programming Language :: Python :: 3.8
Classifier: Programming Language :: Python :: 3.9
Classifier: Programming Language :: Python :: 3.10
Classifier: Programming Language :: Python :: 3.11
Classifier: Programming Language :: Python :: 3.12
Classifier: Programming Language :: Python :: 3.13
Classifier: Programming Language :: Python :: Implementation :: CPython
Classifier: Topic :: Terminals
Requires-Python: >=3.8
License-File: LICENSE
Dynamic: license-file
